odoo/addons/sm_pocketbook/__init__.py
odoo/addons/sm_pocketbook/__manifest__.py
odoo/addons/sm_pocketbook/models/__init__.py
odoo/addons/sm_pocketbook/models/models_pocketbook_history.py
odoo/addons/sm_pocketbook/models/models_pocketbook_record.py
odoo/addons/sm_pocketbook/models/models_pocketbook_record_history.py
odoo/addons/sm_pocketbook/models/models_sm_member.py
odoo/addons/sm_pocketbook/security/ir.model.access.csv
odoo/addons/sm_pocketbook/views/views_members.xml
odoo/addons/sm_pocketbook/views/views_pocketbook_history.xml
odoo/addons/sm_pocketbook/views/views_pocketbook_record.xml
odoo/addons/sm_pocketbook/views/views_pocketbook_record_history.xml
odoo11_addon_sm_pocketbook-11.0.0.0.2.dist-info/METADATA
odoo11_addon_sm_pocketbook-11.0.0.0.2.dist-info/WHEEL
odoo11_addon_sm_pocketbook-11.0.0.0.2.dist-info/top_level.txt
odoo11_addon_sm_pocketbook-11.0.0.0.2.dist-info/RECORD
